{
  "date": "2026-07-22",
  "level": "n5",
  "title": "映画館で映画を見た",
  "text": "きのう、友達と映画館へ行きました。おもしろい映画を見ました。ポップコーンを食べながら、映画を見ました。映画のあとで、カフェでコーヒーを飲みました。とても楽しい一日でした。",
  "tokens": [
    { "surface_form": "きのう", "basic_form": "きのう", "reading": "きのう", "pos": "名詞" },
    { "surface_form": "、", "basic_form": "、", "reading": "、", "pos": "記号" },
    { "surface_form": "友達", "basic_form": "友達", "reading": "ともだち", "pos": "名詞" },
    { "surface_form": "と", "basic_form": "と", "reading": "と", "pos": "助詞" },
    { "surface_form": "映画館", "basic_form": "映画館", "reading": "えいがかん", "pos": "名詞" },
    { "surface_form": "へ", "basic_form": "へ", "reading": "へ", "pos": "助詞" },
    { "surface_form": "行きました", "basic_form": "行く", "reading": "いきました", "pos": "動詞" },
    { "surface_form": "。", "basic_form": "。", "reading": "。", "pos": "記号" },
    { "surface_form": "おもしろい", "basic_form": "おもしろい", "reading": "おもしろい", "pos": "形容詞" },
    { "surface_form": "映画", "basic_form": "映画", "reading": "えいが", "pos": "名詞" },
    { "surface_form": "を", "basic_form": "を", "reading": "を", "pos": "助詞" },
    { "surface_form": "見ました", "basic_form": "見る", "reading": "みました", "pos": "動詞" },
    { "surface_form": "。", "basic_form": "。", "reading": "。", "pos": "記号" },
    { "surface_form": "ポップコーン", "basic_form": "ポップコーン", "reading": "ポップコーン", "pos": "名詞" },
    { "surface_form": "を", "basic_form": "を", "reading": "を", "pos": "助詞" },
    { "surface_form": "食べながら", "basic_form": "食べる", "reading": "たべながら", "pos": "動詞" },
    { "surface_form": "、", "basic_form": "、", "reading": "、", "pos": "記号" },
    { "surface_form": "映画", "basic_form": "映画", "reading": "えいが", "pos": "名詞" },
    { "surface_form": "を", "basic_form": "を", "reading": "を", "pos": "助詞" },
    { "surface_form": "見ました", "basic_form": "見る", "reading": "みました", "pos": "動詞" },
    { "surface_form": "。", "basic_form": "。", "reading": "。", "pos": "記号" },
    { "surface_form": "映画", "basic_form": "映画", "reading": "えいが", "pos": "名詞" },
    { "surface_form": "の", "basic_form": "の", "reading": "の", "pos": "助詞" },
    { "surface_form": "あと", "basic_form": "あと", "reading": "あと", "pos": "名詞" },
    { "surface_form": "で", "basic_form": "で", "reading": "で", "pos": "助詞" },
    { "surface_form": "、", "basic_form": "、", "reading": "、", "pos": "記号" },
    { "surface_form": "カフェ", "basic_form": "カフェ", "reading": "カフェ", "pos": "名詞" },
    { "surface_form": "で", "basic_form": "で", "reading": "で", "pos": "助詞" },
    { "surface_form": "コーヒー", "basic_form": "コーヒー", "reading": "コーヒー", "pos": "名詞" },
    { "surface_form": "を", "basic_form": "を", "reading": "を", "pos": "助詞" },
    { "surface_form": "飲みました", "basic_form": "飲む", "reading": "のみました", "pos": "動詞" },
    { "surface_form": "。", "basic_form": "。", "reading": "。", "pos": "記号" },
    { "surface_form": "とても", "basic_form": "とても", "reading": "とても", "pos": "副詞" },
    { "surface_form": "楽しい", "basic_form": "楽しい", "reading": "たのしい", "pos": "形容詞" },
    { "surface_form": "一日", "basic_form": "一日", "reading": "いちにち", "pos": "名詞" },
    { "surface_form": "でした", "basic_form": "です", "reading": "でした", "pos": "助動詞" },
    { "surface_form": "。", "basic_form": "。", "reading": "。", "pos": "記号" }
  ],
  "vocab": {
    "きのう": { "meaning": "昨天" },
    "友達": { "meaning": "朋友" },
    "映画館": { "meaning": "電影院" },
    "行く": { "meaning": "去" },
    "おもしろい": { "meaning": "有趣的" },
    "映画": { "meaning": "電影" },
    "見る": { "meaning": "看" },
    "ポップコーン": { "meaning": "爆米花" },
    "食べる": { "meaning": "吃" },
    "あと": { "meaning": "之後" },
    "カフェ": { "meaning": "咖啡廳" },
    "コーヒー": { "meaning": "咖啡" },
    "飲む": { "meaning": "喝" },
    "とても": { "meaning": "非常" },
    "楽しい": { "meaning": "開心的" },
    "一日": { "meaning": "一天" }
  },
  "particles": {
    "と": "表示動作的共同對象，相當於「和～一起」",
    "へ": "表示移動的方向",
    "を": "表示動作的對象（受詞）",
    "の": "連接兩個名詞，表示所屬或說明關係",
    "で": "表示動作發生的場所，或時間點之後的接續"
  },
  "translations": [
    [ { "text": "昨天和朋友一起去了電影院。", "word": "行く" } ],
    [ { "text": "看了一部有趣的電影。", "word": "見る" } ],
    [ { "text": "一邊吃爆米花，一邊看電影。", "word": "食べる" } ],
    [ { "text": "電影結束後，在咖啡廳喝了咖啡。", "word": "飲む" } ],
    [ { "text": "是非常開心的一天。", "word": "楽しい" } ]
  ]
}
