{
  "date": "2026-07-21",
  "level": "n2_lite",
  "title": "キャッシュレス決済の広がり",
  "text": "近年、スマートフォンひとつで支払いができるキャッシュレス決済が急速に広がっている。以前は現金しか使えない店も多かったが、最近ではコンビニや飲食店はもちろん、小さな商店街の店でも対応が進んでいる。利用者にとっては財布を持ち歩かなくて済むという利便性がある一方、停電やシステム障害の際に支払いができなくなるという懸念も指摘されている。高齢者の中には操作に不安を感じる人も少なくなく、店舗側には丁寧な説明が求められている。今後は使いやすさと安心感を両立させる工夫が課題になるだろう。",
  "tokens": [
    { "surface_form": "近年", "basic_form": "近年", "reading": "きんねん", "pos": "名詞" },
    { "surface_form": "、", "basic_form": "、", "reading": "、", "pos": "記号" },
    { "surface_form": "スマートフォン", "basic_form": "スマートフォン", "reading": "すまーとふぉん", "pos": "名詞" },
    { "surface_form": "ひとつ", "basic_form": "ひとつ", "reading": "ひとつ", "pos": "名詞" },
    { "surface_form": "で", "basic_form": "で", "reading": "で", "pos": "助詞" },
    { "surface_form": "支払い", "basic_form": "支払い", "reading": "しはらい", "pos": "名詞" },
    { "surface_form": "が", "basic_form": "が", "reading": "が", "pos": "助詞" },
    { "surface_form": "できる", "basic_form": "できる", "reading": "できる", "pos": "動詞" },
    { "surface_form": "キャッシュレス決済", "basic_form": "キャッシュレス決済", "reading": "きゃっしゅれすけっさい", "pos": "名詞" },
    { "surface_form": "が", "basic_form": "が", "reading": "が", "pos": "助詞" },
    { "surface_form": "急速に", "basic_form": "急速", "reading": "きゅうそくに", "pos": "副詞" },
    { "surface_form": "広がっている", "basic_form": "広がる", "reading": "ひろがっている", "pos": "動詞" },
    { "surface_form": "。", "basic_form": "。", "reading": "。", "pos": "記号" },
    { "surface_form": "以前", "basic_form": "以前", "reading": "いぜん", "pos": "名詞" },
    { "surface_form": "は", "basic_form": "は", "reading": "は", "pos": "助詞" },
    { "surface_form": "現金", "basic_form": "現金", "reading": "げんきん", "pos": "名詞" },
    { "surface_form": "しか", "basic_form": "しか", "reading": "しか", "pos": "助詞" },
    { "surface_form": "使えない", "basic_form": "使える", "reading": "つかえない", "pos": "動詞" },
    { "surface_form": "店", "basic_form": "店", "reading": "みせ", "pos": "名詞" },
    { "surface_form": "も", "basic_form": "も", "reading": "も", "pos": "助詞" },
    { "surface_form": "多かった", "basic_form": "多い", "reading": "おおかった", "pos": "形容詞" },
    { "surface_form": "が", "basic_form": "が", "reading": "が", "pos": "助詞" },
    { "surface_form": "、", "basic_form": "、", "reading": "、", "pos": "記号" },
    { "surface_form": "最近", "basic_form": "最近", "reading": "さいきん", "pos": "名詞" },
    { "surface_form": "で", "basic_form": "で", "reading": "で", "pos": "助詞" },
    { "surface_form": "は", "basic_form": "は", "reading": "は", "pos": "助詞" },
    { "surface_form": "コンビニ", "basic_form": "コンビニ", "reading": "こんびに", "pos": "名詞" },
    { "surface_form": "や", "basic_form": "や", "reading": "や", "pos": "助詞" },
    { "surface_form": "飲食店", "basic_form": "飲食店", "reading": "いんしょくてん", "pos": "名詞" },
    { "surface_form": "は", "basic_form": "は", "reading": "は", "pos": "助詞" },
    { "surface_form": "もちろん", "basic_form": "もちろん", "reading": "もちろん", "pos": "副詞" },
    { "surface_form": "、", "basic_form": "、", "reading": "、", "pos": "記号" },
    { "surface_form": "小さな", "basic_form": "小さな", "reading": "ちいさな", "pos": "連体詞" },
    { "surface_form": "商店街", "basic_form": "商店街", "reading": "しょうてんがい", "pos": "名詞" },
    { "surface_form": "の", "basic_form": "の", "reading": "の", "pos": "助詞" },
    { "surface_form": "店", "basic_form": "店", "reading": "みせ", "pos": "名詞" },
    { "surface_form": "で", "basic_form": "で", "reading": "で", "pos": "助詞" },
    { "surface_form": "も", "basic_form": "も", "reading": "も", "pos": "助詞" },
    { "surface_form": "対応", "basic_form": "対応", "reading": "たいおう", "pos": "名詞" },
    { "surface_form": "が", "basic_form": "が", "reading": "が", "pos": "助詞" },
    { "surface_form": "進んでいる", "basic_form": "進む", "reading": "すすんでいる", "pos": "動詞" },
    { "surface_form": "。", "basic_form": "。", "reading": "。", "pos": "記号" },
    { "surface_form": "利用者", "basic_form": "利用者", "reading": "りようしゃ", "pos": "名詞" },
    { "surface_form": "にとって", "basic_form": "にとって", "reading": "にとって", "pos": "助詞" },
    { "surface_form": "は", "basic_form": "は", "reading": "は", "pos": "助詞" },
    { "surface_form": "財布", "basic_form": "財布", "reading": "さいふ", "pos": "名詞" },
    { "surface_form": "を", "basic_form": "を", "reading": "を", "pos": "助詞" },
    { "surface_form": "持ち歩かなくて", "basic_form": "持ち歩く", "reading": "もちあるかなくて", "pos": "動詞" },
    { "surface_form": "済む", "basic_form": "済む", "reading": "すむ", "pos": "動詞" },
    { "surface_form": "という", "basic_form": "という", "reading": "という", "pos": "助詞" },
    { "surface_form": "利便性", "basic_form": "利便性", "reading": "りべんせい", "pos": "名詞" },
    { "surface_form": "が", "basic_form": "が", "reading": "が", "pos": "助詞" },
    { "surface_form": "ある", "basic_form": "ある", "reading": "ある", "pos": "動詞" },
    { "surface_form": "一方", "basic_form": "一方", "reading": "いっぽう", "pos": "名詞" },
    { "surface_form": "、", "basic_form": "、", "reading": "、", "pos": "記号" },
    { "surface_form": "停電", "basic_form": "停電", "reading": "ていでん", "pos": "名詞" },
    { "surface_form": "や", "basic_form": "や", "reading": "や", "pos": "助詞" },
    { "surface_form": "システム障害", "basic_form": "システム障害", "reading": "しすてむしょうがい", "pos": "名詞" },
    { "surface_form": "の", "basic_form": "の", "reading": "の", "pos": "助詞" },
    { "surface_form": "際", "basic_form": "際", "reading": "さい", "pos": "名詞" },
    { "surface_form": "に", "basic_form": "に", "reading": "に", "pos": "助詞" },
    { "surface_form": "支払い", "basic_form": "支払い", "reading": "しはらい", "pos": "名詞" },
    { "surface_form": "が", "basic_form": "が", "reading": "が", "pos": "助詞" },
    { "surface_form": "できなくなる", "basic_form": "できる", "reading": "できなくなる", "pos": "動詞" },
    { "surface_form": "という", "basic_form": "という", "reading": "という", "pos": "助詞" },
    { "surface_form": "懸念", "basic_form": "懸念", "reading": "けねん", "pos": "名詞" },
    { "surface_form": "も", "basic_form": "も", "reading": "も", "pos": "助詞" },
    { "surface_form": "指摘されている", "basic_form": "指摘する", "reading": "してきされている", "pos": "動詞" },
    { "surface_form": "。", "basic_form": "。", "reading": "。", "pos": "記号" },
    { "surface_form": "高齢者", "basic_form": "高齢者", "reading": "こうれいしゃ", "pos": "名詞" },
    { "surface_form": "の", "basic_form": "の", "reading": "の", "pos": "助詞" },
    { "surface_form": "中", "basic_form": "中", "reading": "なか", "pos": "名詞" },
    { "surface_form": "に", "basic_form": "に", "reading": "に", "pos": "助詞" },
    { "surface_form": "は", "basic_form": "は", "reading": "は", "pos": "助詞" },
    { "surface_form": "操作", "basic_form": "操作", "reading": "そうさ", "pos": "名詞" },
    { "surface_form": "に", "basic_form": "に", "reading": "に", "pos": "助詞" },
    { "surface_form": "不安", "basic_form": "不安", "reading": "ふあん", "pos": "名詞" },
    { "surface_form": "を", "basic_form": "を", "reading": "を", "pos": "助詞" },
    { "surface_form": "感じる", "basic_form": "感じる", "reading": "かんじる", "pos": "動詞" },
    { "surface_form": "人", "basic_form": "人", "reading": "ひと", "pos": "名詞" },
    { "surface_form": "も", "basic_form": "も", "reading": "も", "pos": "助詞" },
    { "surface_form": "少なくなく", "basic_form": "少ない", "reading": "すくなくなく", "pos": "形容詞" },
    { "surface_form": "、", "basic_form": "、", "reading": "、", "pos": "記号" },
    { "surface_form": "店舗側", "basic_form": "店舗側", "reading": "てんぽがわ", "pos": "名詞" },
    { "surface_form": "に", "basic_form": "に", "reading": "に", "pos": "助詞" },
    { "surface_form": "は", "basic_form": "は", "reading": "は", "pos": "助詞" },
    { "surface_form": "丁寧な", "basic_form": "丁寧", "reading": "ていねいな", "pos": "形状詞" },
    { "surface_form": "説明", "basic_form": "説明", "reading": "せつめい", "pos": "名詞" },
    { "surface_form": "が", "basic_form": "が", "reading": "が", "pos": "助詞" },
    { "surface_form": "求められている", "basic_form": "求める", "reading": "もとめられている", "pos": "動詞" },
    { "surface_form": "。", "basic_form": "。", "reading": "。", "pos": "記号" },
    { "surface_form": "今後", "basic_form": "今後", "reading": "こんご", "pos": "名詞" },
    { "surface_form": "は", "basic_form": "は", "reading": "は", "pos": "助詞" },
    { "surface_form": "使いやすさ", "basic_form": "使いやすさ", "reading": "つかいやすさ", "pos": "名詞" },
    { "surface_form": "と", "basic_form": "と", "reading": "と", "pos": "助詞" },
    { "surface_form": "安心感", "basic_form": "安心感", "reading": "あんしんかん", "pos": "名詞" },
    { "surface_form": "を", "basic_form": "を", "reading": "を", "pos": "助詞" },
    { "surface_form": "両立させる", "basic_form": "両立させる", "reading": "りょうりつさせる", "pos": "動詞" },
    { "surface_form": "工夫", "basic_form": "工夫", "reading": "くふう", "pos": "名詞" },
    { "surface_form": "が", "basic_form": "が", "reading": "が", "pos": "助詞" },
    { "surface_form": "課題", "basic_form": "課題", "reading": "かだい", "pos": "名詞" },
    { "surface_form": "に", "basic_form": "に", "reading": "に", "pos": "助詞" },
    { "surface_form": "なる", "basic_form": "なる", "reading": "なる", "pos": "動詞" },
    { "surface_form": "だろう", "basic_form": "だろう", "reading": "だろう", "pos": "助動詞" },
    { "surface_form": "。", "basic_form": "。", "reading": "。", "pos": "記号" }
  ],
  "vocab": {
    "近年": { "meaning": "近年來" },
    "スマートフォン": { "meaning": "智慧型手機" },
    "ひとつ": { "meaning": "一個" },
    "支払い": { "meaning": "支付" },
    "できる": { "meaning": "能夠、可以" },
    "キャッシュレス決済": { "meaning": "無現金支付" },
    "急速": { "meaning": "快速、急速" },
    "広がる": { "meaning": "擴大、普及" },
    "以前": { "meaning": "以前" },
    "現金": { "meaning": "現金" },
    "使える": { "meaning": "可以使用" },
    "店": { "meaning": "店家" },
    "多い": { "meaning": "多的" },
    "最近": { "meaning": "最近" },
    "コンビニ": { "meaning": "便利商店" },
    "飲食店": { "meaning": "餐飲店" },
    "もちろん": { "meaning": "當然" },
    "小さな": { "meaning": "小的" },
    "商店街": { "meaning": "商店街" },
    "対応": { "meaning": "因應、對應" },
    "進む": { "meaning": "進展" },
    "利用者": { "meaning": "使用者" },
    "財布": { "meaning": "錢包" },
    "持ち歩く": { "meaning": "隨身攜帶" },
    "済む": { "meaning": "了事、足夠" },
    "という": { "meaning": "叫做、所謂的" },
    "利便性": { "meaning": "便利性" },
    "ある": { "meaning": "有（表示存在）" },
    "一方": { "meaning": "另一方面" },
    "停電": { "meaning": "停電" },
    "システム障害": { "meaning": "系統故障" },
    "際": { "meaning": "～之際、～的時候" },
    "懸念": { "meaning": "擔憂、疑慮" },
    "指摘する": { "meaning": "指出" },
    "高齢者": { "meaning": "高齡者" },
    "中": { "meaning": "裡面、之中" },
    "操作": { "meaning": "操作" },
    "不安": { "meaning": "不安" },
    "感じる": { "meaning": "感覺" },
    "人": { "meaning": "人" },
    "少ない": { "meaning": "少的" },
    "店舗側": { "meaning": "店家方面" },
    "丁寧": { "meaning": "仔細、周到" },
    "説明": { "meaning": "說明" },
    "求める": { "meaning": "要求、尋求" },
    "今後": { "meaning": "今後" },
    "使いやすさ": { "meaning": "易用性" },
    "安心感": { "meaning": "安心感" },
    "両立させる": { "meaning": "使兩者兼顧" },
    "工夫": { "meaning": "巧思、設法" },
    "課題": { "meaning": "課題、待解決的問題" },
    "なる": { "meaning": "變成" }
  },
  "particles": {
    "で": "表示動作發生的場所或方法",
    "が": "主格助詞，標示動作或狀態的主體",
    "は": "主題助詞，用來提示句子的主題",
    "しか": "表示「僅、只」，後面必接否定形式",
    "や": "列舉助詞，「～和～等」，表示不完全列舉",
    "も": "表示「也」，用於類推或並列",
    "の": "所有格助詞，表示「的」或修飾關係",
    "にとって": "表示立場，「對～而言」",
    "という": "表示「叫做、所謂的」，用於說明或引述",
    "を": "受格助詞，標示動作的對象",
    "に": "表示對象、時間點或轉變的結果",
    "と": "表示並列的對象，「～和～」",
    "だろう": "表示推測，「大概～吧」"
  },
  "translations": [
    [ { "text": "近年來，只要一支智慧型手機就能完成支付的無現金支付方式正快速普及。", "word": "キャッシュレス決済" } ],
    [ { "text": "以前只能用現金的店家很多，但最近便利商店和餐飲店自不用說，連小商店街的店家也逐漸能因應了。", "word": "商店街" } ],
    [ { "text": "對使用者而言，不用隨身攜帶錢包很方便，但另一方面也有人擔心停電或系統故障時將無法支付。", "word": "利便性" } ],
    [ { "text": "高齡者當中不少人對操作感到不安，因此店家被要求提供更仔細的說明。", "word": "不安" } ],
    [ { "text": "今後如何兼顧易用性與安心感，將會是一大課題。", "word": "課題" } ]
  ]
}
